pato/__init__.py
pato/lovo.py
pato/ubclient.py
pato/ubsession.py
pato/voiceclient.py
pato/voices.py
uberpato-0.0.5.dist-info/LICENSE
uberpato-0.0.5.dist-info/METADATA
uberpato-0.0.5.dist-info/WHEEL
uberpato-0.0.5.dist-info/top_level.txt
uberpato-0.0.5.dist-info/RECORD
