Metadata-Version: 2.1
Name: uberpato
Version: 0.0.5
Summary: Convenient calling of your favorite TTS APIs
Home-page: https://github.com/uberduck-ai/pato
Author: Uberduck
Author-email: s@uberduck.ai
License: MIT
License-File: LICENSE
Requires-Dist: requests
Requires-Dist: boto3
Requires-Dist: azure-cognitiveservices-speech
